cdktf/__init__.py
cdktf/py.typed
cdktf/_jsii/__init__.py
cdktf/_jsii/cdktf@0.20.10.jsii.tgz
cdktf/testing_matchers/__init__.py
cdktf-0.20.10.dist-info/LICENSE
cdktf-0.20.10.dist-info/METADATA
cdktf-0.20.10.dist-info/WHEEL
cdktf-0.20.10.dist-info/top_level.txt
cdktf-0.20.10.dist-info/RECORD
