Metadata-Version: 2.1
Name: cdktf
Version: 0.20.10
Summary: Cloud Development Kit for Terraform
Home-page: https://github.com/hashicorp/terraform-cdk
Author: HashiCorp
License: MPL-2.0
Project-URL: Source, https://github.com/hashicorp/terraform-cdk.git
Classifier: Intended Audience :: Developers
Classifier: Operating System :: OS Independent
Classifier: Programming Language :: JavaScript
Classifier: Programming Language :: Python :: 3 :: Only
Classifier: Programming Language :: Python :: 3.8
Classifier: Programming Language :: Python :: 3.9
Classifier: Programming Language :: Python :: 3.10
Classifier: Programming Language :: Python :: 3.11
Classifier: Typing :: Typed
Classifier: Development Status :: 4 - Beta
Classifier: License :: OSI Approved
Requires-Python: ~=3.8
License-File: LICENSE
Requires-Dist: constructs<11.0.0,>=10.3.0
Requires-Dist: jsii<2.0.0,>=1.102.0
Requires-Dist: publication>=0.0.3
Requires-Dist: typeguard~=2.13.3
